[{"validatorVoteKey":"CwSZ17woioM2bqEbaswZJYvx5pemN6t3shBcU6zqPHyG","epoch":931,"stakeLamports":"4428509484116","pricePer1KSol":"12135591","amountVSol":"47213573"},{"validatorVoteKey":"4qvFxnUXYjBdcviCwVV7gKcGJMCENEBfS82hSLJUhyvu","epoch":931,"stakeLamports":"4428509484116","pricePer1KSol":"11901241","amountVSol":"46301834"},{"validatorVoteKey":"J1to3PQfXidUUhprQWgdKkQAMWPJAEqSJ7amkBDE9qhF","epoch":931,"stakeLamports":"0","pricePer1KSol":"0","amountVSol":"0"},{"validatorVoteKey":"7K8DVxtNJGnMtUY1CQJT5jcs8sFGSZTDiG7kowvFpECh","epoch":931,"stakeLamports":"4428509484116","pricePer1KSol":"11901241","amountVSol":"46301834"},{"validatorVoteKey":"GA2t11gJcmuZ4y7pShTzgYDkxVaJaVQJqkVUqojhPPsT","epoch":931,"stakeLamports":"4428509484116","pricePer1KSol":"11365111","amountVSol":"44216017"},{"validatorVoteKey":"DfpdmTsSCBPxCDwZwgBMfjjV8mF8xHkGRcXP8dJBVmrq","epoch":931,"stakeLamports":"4428491972893","pricePer1KSol":"11901241","amountVSol":"46301651"},{"validatorVoteKey":"Ac1beBKixfNdrTAac7GRaTsJTxLyvgGvJjvy4qQfvyfc","epoch":931,"stakeLamports":"4428373566584","pricePer1KSol":"12135591","amountVSol":"47212124"},{"validatorVoteKey":"pENgUh4K9zNacyU3PXVE9KugW98XCqZsWpEvA8d8wzX","epoch":931,"stakeLamports":"0","pricePer1KSol":"0","amountVSol":"0"},{"validatorVoteKey":"G1juWDqojmp5CWDhgRqtXrtpAFw9xqhjmEQAKr9faf4V","epoch":931,"stakeLamports":"0","pricePer1KSol":"0","amountVSol":"0"},{"validatorVoteKey":"3xjfK9C9YNcta8MvK1US4sQ3bc6DEjoJoR3qLExGf9xE","epoch":931,"stakeLamports":"11071273710290","pricePer1KSol":"9220593","amountVSol":"89681900"},{"validatorVoteKey":"fVotEjqpmpQYgyVyBCwYm62BKqqTQNE6SpYnRmdBazH","epoch":931,"stakeLamports":"0","pricePer1KSol":"0","amountVSol":"0"},{"validatorVoteKey":"4m1PbxzwLdUnEwog3T9UKxgjktgriHgE1CfAhMqDw7Xx","epoch":931,"stakeLamports":"4428509484116","pricePer1KSol":"0","amountVSol":"0"},{"validatorVoteKey":"FACqsS19VScz8oo2YhdMg35EsAy6xsCZ9Y58eJXGv8QJ","epoch":931,"stakeLamports":"4428509484116","pricePer1KSol":"12018416","amountVSol":"46757704"},{"validatorVoteKey":"Gvt8s5Bwnhg4G27VbnT1Zkfh7Jsztq6CNvZcc5anPonS","epoch":931,"stakeLamports":"15499783194406","pricePer1KSol":"0","amountVSol":"0"},{"validatorVoteKey":"sagasJDjjAHND4hien3bbo5xXkzCT5Ss6nKjyUJ45aw","epoch":931,"stakeLamports":"4428509484116","pricePer1KSol":"12135591","amountVSol":"47213573"},{"validatorVoteKey":"6JfBwvcz5QUKQJ37BMKTLrf968DDJBtwoZLw19aHwFtQ","epoch":931,"stakeLamports":"15499783194406","pricePer1KSol":"9220593","amountVSol":"125554661"},{"validatorVoteKey":"5iZ5PQPy5Z9XDnkfoWPi6nvUgtxWnRFwZ36WaftPuaVM","epoch":931,"stakeLamports":"11065304354199","pricePer1KSol":"9220593","amountVSol":"89633546"},{"validatorVoteKey":"EfnywDKqArxK6N6FS9ctsuzNdxfx3pzfXEQE5EevQ1SV","epoch":931,"stakeLamports":"4428509484116","pricePer1KSol":"11901241","amountVSol":"46301834"},{"validatorVoteKey":"xLabsqDpN9WHXEXSJXk1yhqh5H8BgcqiBP1CR6Mkjcb","epoch":931,"stakeLamports":"1025497698878","pricePer1KSol":"11901241","amountVSol":"10721987"},{"validatorVoteKey":"D3QPJm7BDzzPeRG51YZSEz3LfV7GvFNu9NkcibzURxuj","epoch":931,"stakeLamports":"15350931587492","pricePer1KSol":"9220593","amountVSol":"124348902"},{"validatorVoteKey":"dedxrPfNqPKBRmUyP9LDkaitpQzU6PD44jA6GP9Ndhk","epoch":931,"stakeLamports":"4428509484116","pricePer1KSol":"11901241","amountVSol":"46301834"},{"validatorVoteKey":"steakxfubt37xYdvuXz7BV5Uhhhk1FyJx9zGHfDcTVr","epoch":931,"stakeLamports":"4428509484116","pricePer1KSol":"11901241","amountVSol":"46301834"},{"validatorVoteKey":"5daP6pZoPSak6UEKuRg2HHjvTPpqqwB113oNamGNKuuZ","epoch":931,"stakeLamports":"4428509484116","pricePer1KSol":"11901241","amountVSol":"46301834"},{"validatorVoteKey":"9ymU1ayh9mZVyDL4dUUtXKtX1wCaFNzZPGutLJgqzuC1","epoch":931,"stakeLamports":"6898056379448","pricePer1KSol":"0","amountVSol":"0"},{"validatorVoteKey":"4FsAxdHQ6HmFrDD7yCwsKNApuA67QYSCMoLAy3NfySxJ","epoch":931,"stakeLamports":"11071273710290","pricePer1KSol":"9220593","amountVSol":"89681900"},{"validatorVoteKey":"PineDoC593nrX16W8ZLWfF5Evb6otv7fRfZMLjPAHe3","epoch":931,"stakeLamports":"4428509484116","pricePer1KSol":"0","amountVSol":"0"},{"validatorVoteKey":"3Xn3K5zeTzs4sURj1PCRaF6rvFg2hPgT49B4SiM998f7","epoch":931,"stakeLamports":"15499783194406","pricePer1KSol":"9220593","amountVSol":"125554661"},{"validatorVoteKey":"76DafWkJ6pGK2hoD41HjrM4xTBhfKqrDYDazv13n5ir1","epoch":931,"stakeLamports":"4428509484116","pricePer1KSol":"11901241","amountVSol":"46301834"},{"validatorVoteKey":"21wUViiyG1g47VZ39ZZsSkFX9nu6bkyfy6jryHGD2TUB","epoch":931,"stakeLamports":"15499783194406","pricePer1KSol":"9220593","amountVSol":"125554661"},{"validatorVoteKey":"gVot34jauJpexBL2YUSPBKsmZ4V2ffmDcRk4yfSEnx8","epoch":931,"stakeLamports":"4428509484116","pricePer1KSol":"0","amountVSol":"0"},{"validatorVoteKey":"CHiaohVV2SQCFhiYP73iQzWT6HxnZqnAZJJqAYTeLAo","epoch":931,"stakeLamports":"4413481077936","pricePer1KSol":"9220593","amountVSol":"35751023"},{"validatorVoteKey":"AY271jdvcyo5VzBiWsMGLEjpZFFrarq8FDydJHLmYgCG","epoch":931,"stakeLamports":"15499783194406","pricePer1KSol":"9220593","amountVSol":"125554661"},{"validatorVoteKey":"91413b9eEvG6UofpSgwdUgH9Lz4QBF1G3J325Bw7JwGR","epoch":931,"stakeLamports":"15499783194406","pricePer1KSol":"9220593","amountVSol":"125554661"},{"validatorVoteKey":"bookLxG3LkSmt4htJ1x9zPw6E34RRMAi7sUn5mM3CNN","epoch":931,"stakeLamports":"4428509484116","pricePer1KSol":"11901241","amountVSol":"46301834"},{"validatorVoteKey":"THWfRpcJSC7oDrNMSCcixTZmCHVBTEVQL4qnd1UTD1x","epoch":931,"stakeLamports":"15499783194406","pricePer1KSol":"9220593","amountVSol":"125554661"},{"validatorVoteKey":"HMk1qny4fvMnajErxjXG5kT89JKV4cx1PKa9zhQBF9ib","epoch":931,"stakeLamports":"4428509484116","pricePer1KSol":"12018416","amountVSol":"46757704"},{"validatorVoteKey":"EpicsoqLdDP8qRn3wQRKTSKAXbjK9dUgFfNPRQS77MQD","epoch":931,"stakeLamports":"0","pricePer1KSol":"0","amountVSol":"0"},{"validatorVoteKey":"1Dadio3JRvpEjY6iSmXmhbGy9RiU8Nxh2GmoVbNusbE","epoch":931,"stakeLamports":"11071252197606","pricePer1KSol":"9220593","amountVSol":"89681726"},{"validatorVoteKey":"DriFTm3wM9ugxhCA1K3wVQMSdC4Dv4LNmyZMmZiuHRpp","epoch":931,"stakeLamports":"0","pricePer1KSol":"0","amountVSol":"0"},{"validatorVoteKey":"sShosKd6uA5c1ZpVMxdsE6do13TLRWSMYsXbSMmNC77","epoch":931,"stakeLamports":"0","pricePer1KSol":"0","amountVSol":"0"},{"validatorVoteKey":"mnvkHm47ZmRKoSWuQZAfXLRiDPiKCq8PWkMWrp1Wwqe","epoch":931,"stakeLamports":"15499783194406","pricePer1KSol":"9220593","amountVSol":"125554661"},{"validatorVoteKey":"6oscGUEkXE8fyWoC4czRKbM1cuLkJNtgRsX1Un6w88Vf","epoch":931,"stakeLamports":"0","pricePer1KSol":"0","amountVSol":"0"},{"validatorVoteKey":"hy1oJTV2kX9acsqpwk7hbteqXFw9VDbWvbxoamFEufW","epoch":931,"stakeLamports":"0","pricePer1KSol":"0","amountVSol":"0"},{"validatorVoteKey":"Fhks5gukimP6vxKYbRY4V1aw888EgHhpdDSscD9V6bub","epoch":931,"stakeLamports":"15499783194406","pricePer1KSol":"9220593","amountVSol":"125554661"},{"validatorVoteKey":"novaoLcuVHSudkW3Cphuhiv82vspN5qzinGCtEbwQxz","epoch":931,"stakeLamports":"4428509484116","pricePer1KSol":"11901241","amountVSol":"46301834"},{"validatorVoteKey":"FahWJg2PkphJaMUUCzdYhXkD5NngUuuFRFD3YCE3BSwb","epoch":931,"stakeLamports":"0","pricePer1KSol":"0","amountVSol":"0"},{"validatorVoteKey":"Va1idkzkB6LEmVFmxWbWU8Ao9qehC62Tjmf68L3uYKj","epoch":931,"stakeLamports":"4428509484116","pricePer1KSol":"12088721","amountVSol":"47031225"},{"validatorVoteKey":"STeaKrJdxdPMww27XJsjRBfrzqfjFT1BxotgQtFyDgx","epoch":931,"stakeLamports":"4428509484116","pricePer1KSol":"12088721","amountVSol":"47031225"},{"validatorVoteKey":"R2D2vs3bJwpNF2ejaB6UW1JdCZ5VstuAmuwxDuUUWNj","epoch":931,"stakeLamports":"0","pricePer1KSol":"0","amountVSol":"0"},{"validatorVoteKey":"EATzgj3KL3NAkaSKv8JFXPJahGueMbvTdVZj4zD9nQiV","epoch":931,"stakeLamports":"5758461925763","pricePer1KSol":"9220593","amountVSol":"46645925"},{"validatorVoteKey":"fdvtuDvWJZ89Z7TmeLjCwxgoLcmoEWNxruV48DvJtfm","epoch":931,"stakeLamports":"4428509484116","pricePer1KSol":"12135591","amountVSol":"47213573"},{"validatorVoteKey":"4RcSXeQbgG1v27M27PNNLhy9PGB6uaJACXUZ3kBVc4kF","epoch":931,"stakeLamports":"4428509484116","pricePer1KSol":"11901241","amountVSol":"46301834"},{"validatorVoteKey":"sfo5vA1fFdPRsvqd8qdePtTnK97Qj6Jj3GupEzmNPjJ","epoch":931,"stakeLamports":"0","pricePer1KSol":"0","amountVSol":"0"},{"validatorVoteKey":"PUFFiNkUHF2DMfbKeUcYTSQckDDtkswfxZCDv5WQqwp","epoch":931,"stakeLamports":"15499783194406","pricePer1KSol":"9220593","amountVSol":"125554661"},{"validatorVoteKey":"Lua298Woc4rgcswL64yfWAL4EW44FgBZeLsKforf6tJ","epoch":931,"stakeLamports":"4428509484116","pricePer1KSol":"11901241","amountVSol":"46301834"},{"validatorVoteKey":"H2tJNyMHnRF6ahCQLQ1sSycM4FGchymuzyYzUqKEuydk","epoch":931,"stakeLamports":"4418627278194","pricePer1KSol":"10993027","amountVSol":"42672985"},{"validatorVoteKey":"3Z1N2Fkfha4ThNiRwN8RnU6U8dkFJ92DH2TFyLWJf8cj","epoch":931,"stakeLamports":"4428509484116","pricePer1KSol":"9220593","amountVSol":"35872760"},{"validatorVoteKey":"DPhzpiNGU9C6576uLsNSHmdi2AxwxpjMsRdh2iVC4TPh","epoch":931,"stakeLamports":"0","pricePer1KSol":"0","amountVSol":"0"},{"validatorVoteKey":"9f7dqiYNBZbgPesAnLeWnKCtxYHSfMg5x1EMZCJwVwG7","epoch":931,"stakeLamports":"11071148352162","pricePer1KSol":"9220593","amountVSol":"89680885"},{"validatorVoteKey":"RSSAw6n7Tvqi5iJc2xvHMfk1bhx47GVqj2pj1bq5NUq","epoch":931,"stakeLamports":"0","pricePer1KSol":"0","amountVSol":"0"},{"validatorVoteKey":"F3scMRjzSvXUa7JoK2uwBjNsYGi5sM84sDzE7FfGBo6o","epoch":931,"stakeLamports":"4428386305067","pricePer1KSol":"11901241","amountVSol":"46300546"},{"validatorVoteKey":"StepeLdhJ2znRjHcZdjwMWsC4nTRURNKQY8Nca82LJp","epoch":931,"stakeLamports":"0","pricePer1KSol":"0","amountVSol":"0"},{"validatorVoteKey":"B1w6SZcyvjyp6zEyStcc8u9AxXAh2AbYvNzMmP9rRKE9","epoch":931,"stakeLamports":"15499763070579","pricePer1KSol":"9220593","amountVSol":"125554498"},{"validatorVoteKey":"gridZ5cMHjWGktAQt6o36NtF7XSv19nJBrW83zmo7BM","epoch":931,"stakeLamports":"0","pricePer1KSol":"0","amountVSol":"0"},{"validatorVoteKey":"H4QVPxS7napq3NEYxqLhxbKi9nJ8s56dD2EQZGsyZ3sb","epoch":931,"stakeLamports":"15499603718577","pricePer1KSol":"9220593","amountVSol":"125553207"},{"validatorVoteKey":"juicQdAnksqZ5Yb8NQwCLjLWhykvXGktxnQCDvMe6Nx","epoch":931,"stakeLamports":"0","pricePer1KSol":"0","amountVSol":"0"},{"validatorVoteKey":"5afRnmkFn1pRU9oussqwk1RRBVyoDgUkL16Jz4qNf574","epoch":931,"stakeLamports":"0","pricePer1KSol":"0","amountVSol":"0"},{"validatorVoteKey":"GREEDkpTvpKzcGvBu9qd36yk6BfjTWPShB67gLWuixMv","epoch":931,"stakeLamports":"4428493609213","pricePer1KSol":"0","amountVSol":"0"},{"validatorVoteKey":"6hkfqeNAbURk7CmAQsP4Qm6WwHVF4LxHupEvQf7Tkrf1","epoch":931,"stakeLamports":"15499609366967","pricePer1KSol":"9220593","amountVSol":"125553253"},{"validatorVoteKey":"EtMSc3MvcDXUr6ChK5GxyFVwTxYA3zqP5XzjE9jwKvSV","epoch":931,"stakeLamports":"4428411315358","pricePer1KSol":"0","amountVSol":"0"},{"validatorVoteKey":"mesh3Px7WMi7Dkxke4ZZBULoKHM6sp37wKtg4DwPqPY","epoch":931,"stakeLamports":"4428389384765","pricePer1KSol":"11901241","amountVSol":"46300578"},{"validatorVoteKey":"ELE2xaC6i6pmeu7bfrYjBv4whBeTAbgwcg5hf2ythiBs","epoch":931,"stakeLamports":"4428370077549","pricePer1KSol":"11901241","amountVSol":"46300376"},{"validatorVoteKey":"LNRmxHyXAzgBkgxDmb4ZefwLAnSv3fdsjPgjmThoa1T","epoch":931,"stakeLamports":"4428509484116","pricePer1KSol":"10480332","amountVSol":"40773780"},{"validatorVoteKey":"stsaYQJUhKZDHSqndGtgo6jgbhVaHBSHhtfVWxCwrhD","epoch":931,"stakeLamports":"0","pricePer1KSol":"0","amountVSol":"0"},{"validatorVoteKey":"radYEig9KGrMTMWbWRFV7LStotQbnLgPaEFHVDsudQz","epoch":931,"stakeLamports":"4428385172723","pricePer1KSol":"11901241","amountVSol":"46300534"},{"validatorVoteKey":"34mSDco9FM8599y4QF1GJvyWUrPixeT3zRNZAvzNXF6x","epoch":931,"stakeLamports":"0","pricePer1KSol":"0","amountVSol":"0"},{"validatorVoteKey":"CogentC52e7kktFfWHwsqSmr8LiS1yAtfqhHcftCPcBJ","epoch":931,"stakeLamports":"0","pricePer1KSol":"0","amountVSol":"0"},{"validatorVoteKey":"noMiSdYbNQmFDrH2qMvYRXXzb5DUvjyPyDkXadzAPUV","epoch":931,"stakeLamports":"4428509484116","pricePer1KSol":"11901241","amountVSol":"46301834"},{"validatorVoteKey":"9Gko8QZBbV5SrEvHKtQHcMrGGSfgFP3KJUozEGifu25x","epoch":931,"stakeLamports":"4428386352630","pricePer1KSol":"11901241","amountVSol":"46300546"},{"validatorVoteKey":"odc2aCE7yWTcV8ApP1cHmVqQZTkLNduqaYyKE1XhpE3","epoch":931,"stakeLamports":"4428374047409","pricePer1KSol":"11901241","amountVSol":"46300417"},{"validatorVoteKey":"STPTPuWoyKzbWawom5DBndxkeRFAjW4PzJ2EjL1qeMW","epoch":931,"stakeLamports":"4428385669934","pricePer1KSol":"11901241","amountVSol":"46300539"},{"validatorVoteKey":"mythxna3hpzXSbaseyR12vu5Vvym1HxS92eCgXLvY7w","epoch":931,"stakeLamports":"4428509484116","pricePer1KSol":"12135591","amountVSol":"47213573"},{"validatorVoteKey":"J1to2NAwajc8hD6E6kujdQiPn1Bbt2mGKKZLY9kSQKdB","epoch":931,"stakeLamports":"0","pricePer1KSol":"0","amountVSol":"0"},{"validatorVoteKey":"o27rnqfNHPwHsRp2xPXXwWzn2q2dGxn6UD4Rt5KMU5h","epoch":931,"stakeLamports":"4428402638028","pricePer1KSol":"11365111","amountVSol":"44214951"},{"validatorVoteKey":"H6rbcwuQtadcv9JvxLM7GEskF6xFXnrNT3iPkk4RfyBE","epoch":931,"stakeLamports":"4428386254829","pricePer1KSol":"11901241","amountVSol":"46300546"},{"validatorVoteKey":"adraBKLNY3DL3pg6SJRDYiMA8BsznaWpUdE42X41gbP","epoch":931,"stakeLamports":"4428385128142","pricePer1KSol":"11901241","amountVSol":"46300533"},{"validatorVoteKey":"2ZiMfQaT59j86HVWCvspuMtBotnVBeTc3BKk3kKpwgKP","epoch":931,"stakeLamports":"15499608045664","pricePer1KSol":"9220593","amountVSol":"125553242"},{"validatorVoteKey":"48oxpSHQkM4sdXUY9NQ8KnEtebzZbyk8uUT7JRdVQNuf","epoch":931,"stakeLamports":"15499488128708","pricePer1KSol":"9220593","amountVSol":"125552271"},{"validatorVoteKey":"7JZTyHRTmzHfmHH89uT9xKSKDVJ1VnNQ1FeTeM4iH3J2","epoch":931,"stakeLamports":"4428386242046","pricePer1KSol":"12018416","amountVSol":"46756403"},{"validatorVoteKey":"Luna8BkZNpZ9DKmszrZYPvFpTr4eJJfxxTnGDwTrYkv","epoch":931,"stakeLamports":"15499606126633","pricePer1KSol":"0","amountVSol":"0"},{"validatorVoteKey":"3QPGLackJy5LKctYYoPGmA4P8ncyE197jdxr1zP2ho8K","epoch":931,"stakeLamports":"15499609332352","pricePer1KSol":"9220593","amountVSol":"125553253"},{"validatorVoteKey":"3ZUQekqiZoybB57y49eqtvSaoonqDwuNbeqEGwN88JkQ","epoch":931,"stakeLamports":"15499612066335","pricePer1KSol":"9220593","amountVSol":"125553275"},{"validatorVoteKey":"vvvvXsU6iG2enDVvs4KeVqS4YrZczTujSv5p3dSeNHx","epoch":931,"stakeLamports":"0","pricePer1KSol":"0","amountVSol":"0"},{"validatorVoteKey":"mintrNtxN3PhAB45Pt41XqyKghTTpqcoBkQTZqh96iR","epoch":931,"stakeLamports":"4428386355651","pricePer1KSol":"12018416","amountVSol":"46756404"},{"validatorVoteKey":"B6nDYYLc2iwYqY3zdmavMmU9GjUL2hf79MkufviM2bXv","epoch":931,"stakeLamports":"0","pricePer1KSol":"0","amountVSol":"0"},{"validatorVoteKey":"jag77EXci8uf5uGmKE5izaYvxBCS5H9U2rxWYh8BUUf","epoch":931,"stakeLamports":"4428429939329","pricePer1KSol":"10292852","amountVSol":"40043669"},{"validatorVoteKey":"GdVBPczdFaPf1GXvx8ByHeA1ZHAHwwmdQEPihH74SXm9","epoch":931,"stakeLamports":"0","pricePer1KSol":"0","amountVSol":"0"},{"validatorVoteKey":"BmMVRAVef2qmJ1tJpG3JwRUtnfEiTbvDw9ZeFEi4wE7D","epoch":931,"stakeLamports":"15499604878093","pricePer1KSol":"9220593","amountVSol":"125553217"},{"validatorVoteKey":"eyeVhGmVEoPSWmQU2wP5WZmMihPBTCk7kMMm4VhuAKS","epoch":931,"stakeLamports":"0","pricePer1KSol":"0","amountVSol":"0"},{"validatorVoteKey":"DPmsofVJ1UMRZADgwYAHotJnazMwohHzRHSoomL6Qcao","epoch":931,"stakeLamports":"0","pricePer1KSol":"0","amountVSol":"0"},{"validatorVoteKey":"EdkhvJYa3kWQkFJAPzmGsQyi1D2JA5a7vwWw4hDuwbt","epoch":931,"stakeLamports":"0","pricePer1KSol":"0","amountVSol":"0"},{"validatorVoteKey":"SoLiDDVm88uWUMk2rQpG7B9wC55a6xveYEz3JnS6tzC","epoch":931,"stakeLamports":"0","pricePer1KSol":"0","amountVSol":"0"},{"validatorVoteKey":"sTach38ebT8jnGH8i2D1g8NDAS6An19whVMnSSWPXt4","epoch":931,"stakeLamports":"0","pricePer1KSol":"0","amountVSol":"0"},{"validatorVoteKey":"6q1VNp8Vy2Go12vb8CwbjUqqj2SXr2JYftJRWs71sW23","epoch":931,"stakeLamports":"4428390240247","pricePer1KSol":"12135591","amountVSol":"47212302"},{"validatorVoteKey":"dcntrKBwh8j5yL62Eg96Z5QjJWv3UXxMu4rqL82w6Cb","epoch":931,"stakeLamports":"4428385252939","pricePer1KSol":"11901241","amountVSol":"46300535"},{"validatorVoteKey":"chrtyiAw8suFRvS7rTcfgcDyNu49bGPNZ2fjSPzNPFr","epoch":931,"stakeLamports":"4428385128215","pricePer1KSol":"11901241","amountVSol":"46300533"},{"validatorVoteKey":"QWmexgr4teHa2ZF85tyf2hvEwBvJ6ioAEr1h8DRjoie","epoch":931,"stakeLamports":"4428386221340","pricePer1KSol":"11901241","amountVSol":"46300545"},{"validatorVoteKey":"74y2qkCaJ5L17hTsz3E8jftNxTBCTvdz4P2L6qTHDW59","epoch":931,"stakeLamports":"4428387321170","pricePer1KSol":"11901241","amountVSol":"46300556"},{"validatorVoteKey":"AbacusTT3yhEFEKkQKjGStDhKDnvSFGpg9EqBwz8FnDF","epoch":931,"stakeLamports":"15499679750935","pricePer1KSol":"9220593","amountVSol":"125553823"},{"validatorVoteKey":"phz34EcgWRCT9otPzRS2JtSzVHxQJk4SovqJvV1TQk8","epoch":931,"stakeLamports":"4428386391329","pricePer1KSol":"11901241","amountVSol":"46300546"},{"validatorVoteKey":"DTELA4aHtJB8zcMJvKgcUjAYfkGcKdRUN77cpFoMVgxz","epoch":931,"stakeLamports":"4428509484116","pricePer1KSol":"11901241","amountVSol":"46301834"},{"validatorVoteKey":"edu1fZt5i82cFm6ujUoyXLMdujWxZyWYC8fkydWHRNT","epoch":931,"stakeLamports":"0","pricePer1KSol":"0","amountVSol":"0"},{"validatorVoteKey":"Defi89YpAhk3Gst1Jpsi3Nhj7yCu5HropESh37SQ2v9g","epoch":931,"stakeLamports":"0","pricePer1KSol":"0","amountVSol":"0"},{"validatorVoteKey":"tri1cHBy47fPyhCvrCf6FnR7Mz6XdSoSBah2FsZVQeT","epoch":931,"stakeLamports":"4428388698966","pricePer1KSol":"11901241","amountVSol":"46300571"},{"validatorVoteKey":"Hx4UJCvf8amGeuW9fPFfTckRoznDHxPSYiU9HuUSZKLT","epoch":931,"stakeLamports":"0","pricePer1KSol":"0","amountVSol":"0"},{"validatorVoteKey":"FgiteGaHbA22Wt4Quzv3muscQtvX7gzVwvUHbFnb3rTJ","epoch":931,"stakeLamports":"4428509484116","pricePer1KSol":"9220593","amountVSol":"35872760"},{"validatorVoteKey":"2QE9X9X4tdDUTYic1DgBBJjU7cWUNPbKYGerCb9KqDQN","epoch":931,"stakeLamports":"0","pricePer1KSol":"0","amountVSol":"0"},{"validatorVoteKey":"nebu1WnZBrFZz5X7sfPWuEqyb8LBSsrXpxaesnK9CRE","epoch":931,"stakeLamports":"11071273710290","pricePer1KSol":"9220593","amountVSol":"89681900"},{"validatorVoteKey":"GNZ1PAAS33davY4Q1BMEpZEpVBtRtGvSpcTH5wYVkkVt","epoch":931,"stakeLamports":"0","pricePer1KSol":"0","amountVSol":"0"},{"validatorVoteKey":"EJHf5N9is5spAF5Kz384tTvTV3CwTka6qzUoZrYm53SV","epoch":931,"stakeLamports":"0","pricePer1KSol":"0","amountVSol":"0"},{"validatorVoteKey":"8D8XL6ovqx15RKwC1XtFyTz6H8JYF2fUsxTnsY4b123P","epoch":931,"stakeLamports":"0","pricePer1KSol":"0","amountVSol":"0"},{"validatorVoteKey":"ALPHAthakWdoUxXJP6z8cjCkwrufcARXqi34EjShtFVT","epoch":931,"stakeLamports":"15499783194406","pricePer1KSol":"9220593","amountVSol":"125554661"},{"validatorVoteKey":"mALLoAbdQrgsnm7kWJyPrhcQcmxfT73t8DaqEkpZNd6","epoch":931,"stakeLamports":"0","pricePer1KSol":"0","amountVSol":"0"},{"validatorVoteKey":"DG6fVEB2Qy1jntvHVPui3R12CMqcwNNnjYPYdsbQ9ACP","epoch":931,"stakeLamports":"4428387594379","pricePer1KSol":"0","amountVSol":"0"},{"validatorVoteKey":"SWnetzxKaKtuysePKKAzdPAk3gqWgPYxg31vet69Xnz","epoch":931,"stakeLamports":"0","pricePer1KSol":"0","amountVSol":"0"},{"validatorVoteKey":"5HScvYkTWL9iojhPv26xK7GqB7oBsj9A2qHCeNRFmdyG","epoch":931,"stakeLamports":"0","pricePer1KSol":"0","amountVSol":"0"},{"validatorVoteKey":"Ebm1XKkMzaFg2L5rzLPBnFHMtpDPa6SWJ7nVUzZUmXmR","epoch":931,"stakeLamports":"15499742360235","pricePer1KSol":"9220593","amountVSol":"125554330"},{"validatorVoteKey":"VALiDsfZKafvvQM5CMHhJd6PeVx9UpeDEC4Zk3WYikz","epoch":931,"stakeLamports":"0","pricePer1KSol":"0","amountVSol":"0"},{"validatorVoteKey":"5szskKdH8nfnUuHTvn9hnhH3Xuvo7RVmcDDvD5WD7yNh","epoch":931,"stakeLamports":"4428321096972","pricePer1KSol":"9220593","amountVSol":"35871234"},{"validatorVoteKey":"unRgBLTLNXdBmenHXNPAg3AMn3KWcV3Mk4eoZBmTrdk","epoch":931,"stakeLamports":"4428509484116","pricePer1KSol":"12135591","amountVSol":"47213573"},{"validatorVoteKey":"7rwEPPMQgHr3mn5nQX27SADt3tR8yucBgsNapYdrqRhB","epoch":931,"stakeLamports":"0","pricePer1KSol":"0","amountVSol":"0"},{"validatorVoteKey":"fuyugZxM5S4NyV3ZYoc6ebs3fmRTrZ3X27MKCFvHpVD","epoch":931,"stakeLamports":"4428386077526","pricePer1KSol":"11901241","amountVSol":"46300543"},{"validatorVoteKey":"FLCrbfbwEhFARa8nK9rnZw8BVtKNAuHujh9EhWy5A4U4","epoch":931,"stakeLamports":"11071273710290","pricePer1KSol":"9220593","amountVSol":"89681900"},{"validatorVoteKey":"pine9rHVDS1pjwdhYkx3vRyaAyRd5KPDKXZEXAqvxcX","epoch":931,"stakeLamports":"0","pricePer1KSol":"0","amountVSol":"0"},{"validatorVoteKey":"MicobSZgB9CZNvmnFSYbEtMjy7CUui5o6P3XoGTwZC5","epoch":931,"stakeLamports":"4428386995916","pricePer1KSol":"12018416","amountVSol":"46756411"},{"validatorVoteKey":"GzjMbJQDVuBLFY69QwhhjDGDy2o5Q6nswXMuVTCWEFnp","epoch":931,"stakeLamports":"4428386387135","pricePer1KSol":"12135591","amountVSol":"47212261"},{"validatorVoteKey":"axyQeKp44XqUnvC1jVHoeuAJ3j8wVnGeWtddeAcNYcF","epoch":931,"stakeLamports":"0","pricePer1KSol":"0","amountVSol":"0"},{"validatorVoteKey":"BiUSTKzDM57pkf52SqxqckEk4ap7d25y2GB4GLXxdgj7","epoch":931,"stakeLamports":"0","pricePer1KSol":"0","amountVSol":"0"},{"validatorVoteKey":"CP6mfD4Qc5AYrboXBAQeHMYj5x1UnYksDXRjG7DMkHH7","epoch":931,"stakeLamports":"0","pricePer1KSol":"0","amountVSol":"0"},{"validatorVoteKey":"bay3rQMjiLPy6Nvi7tfNeVK26inBCxf88hKYyeKy64H","epoch":931,"stakeLamports":"15499603737784","pricePer1KSol":"9220593","amountVSol":"125553207"},{"validatorVoteKey":"3a2onvgTpGynakAQwx6gigtSeL7itZewNxqb5JiAvWeA","epoch":931,"stakeLamports":"0","pricePer1KSol":"0","amountVSol":"0"},{"validatorVoteKey":"LimeNKYH66uR9BwnrPtxPbpqmkambxHVcutGoSaWPiq","epoch":931,"stakeLamports":"4428461213402","pricePer1KSol":"9337768","amountVSol":"36328234"},{"validatorVoteKey":"CNcaYdqkCwxDpKSVK8in5f6kqrTiZ5SuHsHFDqx6jNvu","epoch":931,"stakeLamports":"0","pricePer1KSol":"0","amountVSol":"0"},{"validatorVoteKey":"StakeyJXE1yJbEApBVswHN4JdZXcj7V5MHbzffa4dFp","epoch":931,"stakeLamports":"4428509484116","pricePer1KSol":"12135591","amountVSol":"47213573"},{"validatorVoteKey":"SWiz8fJt7CV99Uv9VZTLGAkMP3vTpc6u7ZqNN5dsWXU","epoch":931,"stakeLamports":"11071144486834","pricePer1KSol":"9220593","amountVSol":"89680854"},{"validatorVoteKey":"prt1s9dMM15LdsUX9HugajzqPB5WVN8a2mw3frAiCfj","epoch":931,"stakeLamports":"4428386149740","pricePer1KSol":"12135591","amountVSol":"47212259"},{"validatorVoteKey":"NeodymeDFipD7eA1ShrLJAZTBdHWcFsDB9YkoHshZNk","epoch":931,"stakeLamports":"0","pricePer1KSol":"0","amountVSol":"0"},{"validatorVoteKey":"CiTYUYPAPHdcri5yEfsmqVcs54J6j8X1QaiFLgYqMVe","epoch":931,"stakeLamports":"15499783194406","pricePer1KSol":"9220593","amountVSol":"125554661"},{"validatorVoteKey":"soLStAckuvkHtNzHF1cwmeSRG1FzVxKxwsdWZ1yrHrz","epoch":931,"stakeLamports":"15499604384599","pricePer1KSol":"9220593","amountVSol":"125553212"},{"validatorVoteKey":"EBVj3uwSKZpqEb1K267JaPxDQhULVqCy6hYeQqjsPh81","epoch":931,"stakeLamports":"4428390544351","pricePer1KSol":"11901241","amountVSol":"46300590"},{"validatorVoteKey":"goJiRADNdmfnJ4iWEyft7KaYMPTVsRba2Ee1akDEBXb","epoch":931,"stakeLamports":"4428386174921","pricePer1KSol":"11901241","amountVSol":"46300545"},{"validatorVoteKey":"57GUg9QH2LFMV11oaduuoqVJ5qHDEp7EGJ2xgkGiqAum","epoch":931,"stakeLamports":"4428433879192","pricePer1KSol":"12135591","amountVSol":"47212768"},{"validatorVoteKey":"sdo2QoiSsPknraeCts5GeBkV3AYDdtuxJ3VpYCS1CxR","epoch":931,"stakeLamports":"4428433879106","pricePer1KSol":"9454943","amountVSol":"36783871"},{"validatorVoteKey":"SKRuTecmFDZHjs2DxRTJNEK7m7hunKGTWJiaZ3tMVVA","epoch":931,"stakeLamports":"0","pricePer1KSol":"0","amountVSol":"0"},{"validatorVoteKey":"5iJDEVRi1nMLwKAWhYbEokZnvBAe15rgFaHGkggVEP9z","epoch":931,"stakeLamports":"11071273710290","pricePer1KSol":"9220593","amountVSol":"89681900"},{"validatorVoteKey":"kyvvvkDpDCtSxQMPhzRhmv14DgUBVEGGzn8Dnb8ircP","epoch":931,"stakeLamports":"4428386216833","pricePer1KSol":"12135591","amountVSol":"47212259"},{"validatorVoteKey":"86Sw9R6ynPmXnHfwUWinXtq1QoF2KHesfQQyZG5r8sXo","epoch":931,"stakeLamports":"4428480388101","pricePer1KSol":"9220593","amountVSol":"35872525"},{"validatorVoteKey":"G1EAMrJcvzs5SwqAQRgDTjYBEGrxxJVwNS7qiUtB3akg","epoch":931,"stakeLamports":"4428386091238","pricePer1KSol":"11901241","amountVSol":"46300544"},{"validatorVoteKey":"4BVYjw1ztUzUPsxsaCheWWwThT2X4rjogZytGnuWPUGg","epoch":931,"stakeLamports":"0","pricePer1KSol":"0","amountVSol":"0"},{"validatorVoteKey":"3iPuTgpWaaC6jYEY7kd993QBthGsQTK3yPCrNJyPMhCD","epoch":931,"stakeLamports":"10562421882631","pricePer1KSol":"0","amountVSol":"0"},{"validatorVoteKey":"9G19HT8xqceG7mKQVSrTRS3DGnGqDHErPyQEaEfyWEuW","epoch":931,"stakeLamports":"11071148295825","pricePer1KSol":"9220593","amountVSol":"89680885"},{"validatorVoteKey":"8jxSHbS4qAnh5yueFp4D9ABXubKqMwXqF3HtdzQGuphp","epoch":931,"stakeLamports":"11071148290095","pricePer1KSol":"9220593","amountVSol":"89680885"},{"validatorVoteKey":"2g2QU1NDRax6i2mKzRwgRfdBFoDkMC6bj7Zp5Q3i8sCq","epoch":931,"stakeLamports":"10974438952456","pricePer1KSol":"9220593","amountVSol":"88897499"},{"validatorVoteKey":"FnAPJkzf19s87sm24Qhv6bHZMZvZ43gjNUBRgjwXpD4v","epoch":931,"stakeLamports":"10808924183626","pricePer1KSol":"9220593","amountVSol":"87556761"},{"validatorVoteKey":"HMV14UAuULSwqmZhsKHzaVkYAd94iWpEeURgbUegfQLc","epoch":931,"stakeLamports":"10968398207143","pricePer1KSol":"0","amountVSol":"0"},{"validatorVoteKey":"323d4ZiSqS1PwGwpJwD88jNPaGqkm7YYW2tJt2T8iFzo","epoch":931,"stakeLamports":"10809857865009","pricePer1KSol":"9220593","amountVSol":"87564324"},{"validatorVoteKey":"4KfAqBj3Jvi9GGngFK1MbZkjHTcSFyvhFnVwc2QrNiEh","epoch":931,"stakeLamports":"9231159503112","pricePer1KSol":"9220593","amountVSol":"74776213"},{"validatorVoteKey":"gfR2VCrsVcm1gF2teasQpP6BdX99mVVFhEQck3UhTNC","epoch":931,"stakeLamports":"10466786848408","pricePer1KSol":"9220593","amountVSol":"84785307"},{"validatorVoteKey":"2ZP7DPXW6gwMRSY9PSXQ75fZLrk4gKWKnT85pK5sVPa5","epoch":931,"stakeLamports":"10235507345507","pricePer1KSol":"9220593","amountVSol":"82911847"},{"validatorVoteKey":"BH2PMb9vuHxkVFMMHbH8iudCoBfUoX5tVaHfnEkKJ2gQ","epoch":931,"stakeLamports":"11071144340303","pricePer1KSol":"9220593","amountVSol":"89680853"},{"validatorVoteKey":"6hcGvZypizjf6PPsxboshZHRqefyQKSG9L8vZqYdm7UY","epoch":931,"stakeLamports":"11071144278318","pricePer1KSol":"9220593","amountVSol":"89680852"},{"validatorVoteKey":"5XGMWvqZSBk1fktPtxbwaMF5dhkbrtchpwd4xiXG9q8u","epoch":931,"stakeLamports":"0","pricePer1KSol":"0","amountVSol":"0"},{"validatorVoteKey":"pt1LsjkNwqCKdYYfc35ToDkqtEG9pswLTJNaMo8inft","epoch":931,"stakeLamports":"0","pricePer1KSol":"0","amountVSol":"0"},{"validatorVoteKey":"BDn3HiXMTym7ZQofWFxDb7ZGQX6GomQzJYKfytTAqd5g","epoch":931,"stakeLamports":"0","pricePer1KSol":"0","amountVSol":"0"}]